README
setup.py
pygdb2/__init__.py
pygdb2/gdb_commands.py
pygdb2.egg-info/PKG-INFO
pygdb2.egg-info/SOURCES.txt
pygdb2.egg-info/dependency_links.txt
pygdb2.egg-info/top_level.txt