Metadata-Version: 1.0
Name: pygdb2
Version: 0.1
Summary: Control GDB from within the Python program being debugged
Home-page: https://bitbucket.org/antocuni/pygdb2/
Author: Antonio Cuni
Author-email: anto.cuni@gmail.com
License: BSD
Platform: unix
Platform: linux
